sqltemplate/__init__.py
sqltemplate/base.py
sqltemplate/dummy_sqlparse.py
sqltemplate/exceptions.py
sqltemplate/models.py
sqltemplate/query.py
sqltemplate/utils.py
sqltemplate/contrib/__init__.py
sqltemplate/contrib/django/__init__.py
sqltemplate/contrib/django/engines.py
sqltemplate/contrib/django/loader.py
sqltemplate/contrib/django/models.py
sqltemplate/contrib/django/settings.py
sqltemplate/contrib/django/loaders/__init__.py
sqltemplate/contrib/django/loaders/app_directories.py
sqltemplate-0.5.4.post1.dist-info/LICENSE
sqltemplate-0.5.4.post1.dist-info/METADATA
sqltemplate-0.5.4.post1.dist-info/WHEEL
sqltemplate-0.5.4.post1.dist-info/top_level.txt
sqltemplate-0.5.4.post1.dist-info/zip-safe
sqltemplate-0.5.4.post1.dist-info/RECORD
